baltra_sdk/__init__.py
baltra_sdk/backend/db/screening_models.py
baltra_sdk/lambdas/db/sql_utils.py
baltra_sdk/lambdas/services/openai_utils.py
baltra_sdk/lambdas/services/whatsapp_messages.py
baltra_sdk/lambdas/services/whatsapp_utils.py
baltra_sdk/lambdas/utils/candidate_data_fetcher.py
baltra_sdk/shared/elevenlabs/elevenlabs_prompt.py
baltra_sdk/shared/email_templates/__init__.py
baltra_sdk/shared/email_templates/email_templates.py
baltra_sdk/shared/funnel_states/funnel_states.py
baltra_sdk-1.0.23.dist-info/METADATA
baltra_sdk-1.0.23.dist-info/WHEEL
baltra_sdk-1.0.23.dist-info/top_level.txt
baltra_sdk-1.0.23.dist-info/RECORD
